immo_tools/__init__.py
immo_tools/calculator.py
immo_tools/constants.py
immo_tools_lib-0.1.3.dist-info/LICENSE
immo_tools_lib-0.1.3.dist-info/WHEEL
immo_tools_lib-0.1.3.dist-info/METADATA
immo_tools_lib-0.1.3.dist-info/RECORD
