Metadata-Version: 2.1
Name: immo-tools-lib
Version: 0.1.3
Summary: calcul des couts de credit immobilier
Home-page: https://github.com/thomas-marquis/immo-tools-lib
License: MIT
Author: thomas.marquis.dev
Author-email: thomas.marquis314@gmail.com
Requires-Python: >=3.7,<4.0
Classifier: License :: OSI Approved :: MIT License
Classifier: Programming Language :: Python :: 3
Classifier: Programming Language :: Python :: 3.7
Classifier: Programming Language :: Python :: 3.8
Requires-Dist: numpy (>=1.18.1,<2.0.0)
Requires-Dist: pandas (>=1.0.1,<2.0.0)
Requires-Dist: tabulate (>=0.8.6,<0.9.0)
Project-URL: Repository, https://github.com/thomas-marquis/immo-tools-lib
